main.py
app/__init__.py
app/asciiclip.py
app/moby.ttf
asciiclip-1.0.1.dist-info/LICENSE
asciiclip-1.0.1.dist-info/METADATA
asciiclip-1.0.1.dist-info/WHEEL
asciiclip-1.0.1.dist-info/entry_points.txt
asciiclip-1.0.1.dist-info/top_level.txt
asciiclip-1.0.1.dist-info/RECORD
