Metadata-Version: 2.1
Name: asciiclip
Version: 1.0.1
Summary: CLI tool that applies an ASCII filter to video or image.
Home-page: https://github.com/leinstay/asciiclip
Author: leinstay
Author-email: leinstay@gmail.com
Classifier: License :: OSI Approved :: MIT License
Classifier: Programming Language :: Python :: 3
Classifier: Operating System :: OS Independent
Classifier: Environment :: Console
Classifier: Topic :: Multimedia :: Video :: Conversion
Classifier: Topic :: Scientific/Engineering :: Image Processing
Classifier: Topic :: Text Processing
Requires-Python: >=3.7
License-File: LICENSE
Requires-Dist: click
Requires-Dist: moviepy
Requires-Dist: pytube
Requires-Dist: Pillow
